<?xml version="1.0" encoding="UTF-8"?>
<objects serializationModel="Studio.02.02.00">
	<object class="AudioFile" id="{e1d31c3a-7022-4dbc-9018-4f4d8c5eea3f}">
		<property name="assetPath">
			<value>SFX_CATHEDRAL1.mp3</value>
		</property>
		<property name="frequencyInKHz">
			<value>44.0999985</value>
		</property>
		<property name="channelCount">
			<value>2</value>
		</property>
		<property name="length">
			<value>3.7355102040816326</value>
		</property>
		<relationship name="masterAssetFolder">
			<destination>{37aca66c-891f-4048-a4f6-cc846adcc445}</destination>
		</relationship>
	</object>
</objects>
